sudoku9/__init__.py
sudoku9/cli.py
sudoku9/generator.py
sudoku9/gui.py
sudoku9/solver.py
sudoku9/utils.py
sudoku9-0.1.0.dist-info/licenses/LICENSE
sudoku9-0.1.0.dist-info/METADATA
sudoku9-0.1.0.dist-info/WHEEL
sudoku9-0.1.0.dist-info/entry_points.txt
sudoku9-0.1.0.dist-info/top_level.txt
sudoku9-0.1.0.dist-info/RECORD
