Metadata-Version: 2.4
Name: sudoku9
Version: 0.1.0
Summary: A Sudoku solver and generator with GUI and CLI support
Author: Kunal Kumar
License: MIT
Project-URL: Homepage, https://github.com/kunalsingh2904/sudoku9
Project-URL: Repository, https://github.com/kunalsingh2904/sudoku9
Project-URL: Issues, https://github.com/kunalsingh2904/sudoku9/issues
Classifier: Programming Language :: Python :: 3.11
Classifier: Programming Language :: Python :: 3.12
Classifier: Programming Language :: Python :: 3.13
Classifier: License :: OSI Approved :: MIT License
Classifier: Operating System :: OS Independent
Classifier: Development Status :: 4 - Beta
Classifier: Intended Audience :: Developers
Classifier: Intended Audience :: End Users/Desktop
Classifier: Topic :: Games/Entertainment :: Puzzle Games
Requires-Python: >=3.11
License-File: LICENSE
Requires-Dist: pyqt6>=6.8.1
Requires-Dist: rich>=14.0.0
Requires-Dist: pyqtdarktheme>=0.1.7
Dynamic: license-file
